cognitive_tracer/__init__.py
cognitive_tracer/tracer.py
llm_reasoning_tracer-0.1.0.dist-info/licenses/LICENSE
llm_reasoning_tracer-0.1.0.dist-info/METADATA
llm_reasoning_tracer-0.1.0.dist-info/WHEEL
llm_reasoning_tracer-0.1.0.dist-info/top_level.txt
llm_reasoning_tracer-0.1.0.dist-info/RECORD
