Metadata-Version: 2.4
Name: llm_reasoning_tracer
Version: 0.1.0
Summary: Trace and explain LangChain agent reasoning step-by-step
Home-page: https://github.com/nisaharan/llm_reasoning_tracer
Author: Nisaharan Genhatharan
Classifier: Programming Language :: Python :: 3
Classifier: License :: OSI Approved :: MIT License
Requires-Python: >=3.8
License-File: LICENSE
Requires-Dist: langchain
Requires-Dist: streamlit
Requires-Dist: openai
Requires-Dist: faiss-cpu
Requires-Dist: tiktoken
Dynamic: author
Dynamic: classifier
Dynamic: description
Dynamic: description-content-type
Dynamic: home-page
Dynamic: license-file
Dynamic: requires-dist
Dynamic: requires-python
Dynamic: summary
